starsep_utils-0.9.2.dist-info/METADATA
starsep_utils-0.9.2.dist-info/WHEEL
starsep_utils-0.9.2.dist-info/entry_points.txt
starsep_utils-0.9.2.dist-info/licenses/LICENSE
starsep_utils/__init__.py
starsep_utils/distance.py
starsep_utils/duplicates.py
starsep_utils/fileSize.py
starsep_utils/healthchecks.py
starsep_utils/logDuration.py
starsep_utils/models.py
starsep_utils/overpass.py
tests/__init__.py
tests/distance_test.py
tests/duplicates_test.py
tests/fileSize_test.py
tests/logDuration_test.py
tests/overpass_test.py
starsep_utils-0.9.2.dist-info/RECORD
